biofes/__init__.py
biofes/biplot.py
biofes/feature.py
biofes-1.0.1.dist-info/LICENSE.md
biofes-1.0.1.dist-info/METADATA
biofes-1.0.1.dist-info/WHEEL
biofes-1.0.1.dist-info/top_level.txt
biofes-1.0.1.dist-info/RECORD
